weavingspace/__init__.py
weavingspace/_loom.py
weavingspace/_tiling_geometries.py
weavingspace/_weave_grid.py
weavingspace/symmetry.py
weavingspace/tile_map.py
weavingspace/tile_unit.py
weavingspace/tileable.py
weavingspace/tiling_utils.py
weavingspace/topology.py
weavingspace/weave_matrices.py
weavingspace/weave_unit.py
weavingspace-0.0.7.13.dist-info/licenses/LICENSE.md
weavingspace-0.0.7.13.dist-info/METADATA
weavingspace-0.0.7.13.dist-info/WHEEL
weavingspace-0.0.7.13.dist-info/top_level.txt
weavingspace-0.0.7.13.dist-info/RECORD
