Metadata-Version: 2.4
Name: weavingspace
Version: 0.0.7.13
Summary: A package for making tiled mapping layers
Author-email: David O'Sullivan <osullivan512@gmail.com>
License-Expression: MIT
Project-URL: Homepage, https://github.com/DOSull/weaving-space
Project-URL: Repository, https://github.com/DOSull/weaving-space
Classifier: Programming Language :: Python :: 3
Classifier: Operating System :: OS Independent
Requires-Python: >=3.12.0
License-File: LICENSE.md
Requires-Dist: requests
Requires-Dist: importlib-metadata; python_version >= "3.12"
Requires-Dist: fiona
Requires-Dist: geopandas
Requires-Dist: mapclassify
Requires-Dist: pandas
Requires-Dist: numpy
Requires-Dist: scipy
Requires-Dist: shapely
Requires-Dist: networkx
Requires-Dist: pillow
Requires-Dist: matplotlib
Requires-Dist: dataclasses
Requires-Dist: typing
Dynamic: license-file
